bayesblend/__init__.py
bayesblend/io.py
bayesblend/models.py
bayesblend/stan_files/hierarchical_stacking.stan
bayesblend/stan_files/hierarchical_stacking_pooling.stan
bayesblend/stan_files/stacking.stan
bayesblend-0.0.8.dist-info/LICENSE
bayesblend-0.0.8.dist-info/METADATA
bayesblend-0.0.8.dist-info/WHEEL
bayesblend-0.0.8.dist-info/RECORD
