Metadata-Version: 2.1
Name: bayesblend
Version: 0.0.8
Summary: Easily combine predictions from multiple Bayesian models using techniques including (pseudo) Bayesian model averaging, hierarchical stacking, and more!
Author: Nathaniel Haines
Author-email: nathaniel.haines@ledgerinvesting.com
Requires-Python: >=3.10,<4.0.0
Classifier: Programming Language :: Python :: 3
Classifier: Programming Language :: Python :: 3.10
Classifier: Programming Language :: Python :: 3.11
Classifier: Programming Language :: Python :: 3.12
Requires-Dist: arviz (>=0.18.0,<0.19.0)
Requires-Dist: cmdstanpy (>=1.2.1,<2.0.0)
Requires-Dist: matplotlib (==3.7.2)
Requires-Dist: scipy (>=1.12.0,<2.0.0)
